ping_game_theory/__init__.py
ping_game_theory/py.typed
ping_game_theory-0.1.4.dist-info/WHEEL
ping_game_theory-0.1.4.dist-info/entry_points.txt
ping_game_theory-0.1.4.dist-info/METADATA
ping_game_theory-0.1.4.dist-info/RECORD
