Metadata-Version: 2.3
Name: ping-game-theory
Version: 0.1.4
Summary: Driver Code for @ping/game-theory-25
Author: lalitm1004, lg28literconvectionmicrowaveoven
Author-email: lalitm1004 <lalitm1004@gmail.com>, lg28literconvectionmicrowaveoven <sabari.girish2057@gmail.com>
Requires-Dist: tqdm>=4.67.1
Requires-Python: >=3.9
